playrip/__main__.py
playrip/cli.py
playrip/Dowload.py
playrip-1.1.62.dist-info/entry_points.txt
playrip-1.1.62.dist-info/METADATA
playrip-1.1.62.dist-info/WHEEL
playrip-1.1.62.dist-info/RECORD
