Metadata-Version: 2.4
Name: playrip
Version: 1.1.62
Summary: Esse projeto é usado para abaixar musicas tanto no spotify e no Youtube
Author: IyinG
Author-email: 165347923+Blackgnr7@users.noreply.github.com
Requires-Python: >=3.10,<4.0
Classifier: Programming Language :: Python :: 3
Classifier: Programming Language :: Python :: 3.10
Classifier: Programming Language :: Python :: 3.11
Classifier: Programming Language :: Python :: 3.12
Classifier: Programming Language :: Python :: 3.13
Classifier: Programming Language :: Python :: 3.14
Requires-Dist: eyeD3 (>=0.9.7)
Requires-Dist: mutagen (>=1.47.0)
Requires-Dist: pydub (>=0.25.1)
Requires-Dist: pytubefix (>=8.0.0)
Requires-Dist: requests (>=2.32.0)
Requires-Dist: spotipy (>=2.24.0)
